a_selenium_better_sendkeys/LICENSE
a_selenium_better_sendkeys/README.MD
a_selenium_better_sendkeys/__init__.py
a_selenium_better_sendkeys/requirements.txt
a_selenium_better_sendkeys/thirdparty.json
a_selenium_better_sendkeys-0.10.dist-info/LICENSE.rst
a_selenium_better_sendkeys-0.10.dist-info/METADATA
a_selenium_better_sendkeys-0.10.dist-info/WHEEL
a_selenium_better_sendkeys-0.10.dist-info/top_level.txt
a_selenium_better_sendkeys-0.10.dist-info/RECORD
